{
  "initial_balance": "1000",
  "cash_balance": "999.9250000000000000000000000",
  "positions": [
    {
      "id": "517310_1769752035881",
      "market_id": "517310",
      "question": "Will Trump deport less than 250,000?",
      "token_id": "101676997363687199724245607342877036148401850938023978421879460310389391082353",
      "side": "Yes",
      "shares": "1248.7512487512487512487512488",
      "entry_price": "0.04004",
      "cost_basis": "50.000000000000000000000000002",
      "current_price": "0.04004",
      "current_value": "50.000000000000000000000000002",
      "unrealized_pnl": "0",
      "unrealized_pnl_pct": "0",
      "exit_price": "0.03999996",
      "realized_pnl": "-0.050000000000000000000000000",
      "status": "ClosedLoss",
      "entry_time": "2026-01-30T05:47:15.881992163Z",
      "exit_time": "2026-01-30T05:47:29.370323920Z",
      "entry_reason": "CLI buy: 517310",
      "exit_reason": "CLI sell"
    },
    {
      "id": "517310_1769752199093",
      "market_id": "517310",
      "question": "Will Trump deport less than 250,000?",
      "token_id": "101676997363687199724245607342877036148401850938023978421879460310389391082353",
      "side": "Yes",
      "shares": "675.000675000675000675000675",
      "entry_price": "0.037037",
      "cost_basis": "25.000000000000000000000000000",
      "current_price": "0.037037",
      "current_value": "25.000000000000000000000000000",
      "unrealized_pnl": "0",
      "unrealized_pnl_pct": "0",
      "exit_price": "0.036999963",
      "realized_pnl": "-0.025000000000000000000000000",
      "status": "ClosedLoss",
      "entry_time": "2026-01-30T05:49:59.093596769Z",
      "exit_time": "2026-01-30T06:27:28.655863311Z",
      "entry_reason": "CLI buy: trump",
      "exit_reason": "CLI sell"
    }
  ],
  "trade_history": [
    {
      "id": "517310_1769752035881",
      "market_id": "517310",
      "question": "Will Trump deport less than 250,000?",
      "side": "Yes",
      "action": "Buy",
      "shares": "1248.7512487512487512487512488",
      "price": "0.04004",
      "total_value": "50",
      "pnl": null,
      "timestamp": "2026-01-30T05:47:15.881992799Z",
      "reason": "CLI buy: 517310"
    },
    {
      "id": "517310_1769752035881_sell",
      "market_id": "517310",
      "question": "Will Trump deport less than 250,000?",
      "side": "Yes",
      "action": "Sell",
      "shares": "1248.7512487512487512487512488",
      "price": "0.03999996",
      "total_value": "49.950000000000000000000000002",
      "pnl": "-0.050000000000000000000000000",
      "timestamp": "2026-01-30T05:47:29.370330063Z",
      "reason": "CLI sell"
    },
    {
      "id": "517310_1769752199093",
      "market_id": "517310",
      "question": "Will Trump deport less than 250,000?",
      "side": "Yes",
      "action": "Buy",
      "shares": "675.000675000675000675000675",
      "price": "0.037037",
      "total_value": "25",
      "pnl": null,
      "timestamp": "2026-01-30T05:49:59.093598466Z",
      "reason": "CLI buy: trump"
    },
    {
      "id": "517310_1769752199093_sell",
      "market_id": "517310",
      "question": "Will Trump deport less than 250,000?",
      "side": "Yes",
      "action": "Sell",
      "shares": "675.000675000675000675000675",
      "price": "0.036999963",
      "total_value": "24.975000000000000000000000000",
      "pnl": "-0.025000000000000000000000000",
      "timestamp": "2026-01-30T06:27:28.655868623Z",
      "reason": "CLI sell"
    }
  ],
  "created_at": "2026-01-30T05:39:27.513594441Z",
  "updated_at": "2026-01-30T06:27:28.655869366Z"
}